vim_session_manager/__init__.py
vim_session_manager/__main__.py
vim_session_manager/cli.py
vim_session_manager/log.py
vim_session_manager/manager.py
vim_session_manager/prompt.py
vim_session_manager/utils.py
vim_session_manager-0.1.5.dist-info/entry_points.txt
vim_session_manager-0.1.5.dist-info/LICENSE
vim_session_manager-0.1.5.dist-info/WHEEL
vim_session_manager-0.1.5.dist-info/METADATA
vim_session_manager-0.1.5.dist-info/RECORD
