Metadata-Version: 2.1
Name: vim-session-manager
Version: 0.1.5
Summary: A small python program for managing vim sessions
Home-page: https://github.com/mattcoding4days/vsm
License: GPL-3.0-only
Keywords: vim,nvim,commandline,mksession
Author: Matt Williams
Author-email: matt.k.williams@protonmail.com
Requires-Python: >=3.10.1,<4.0.0
Classifier: License :: OSI Approved :: GNU General Public License v3 (GPLv3)
Classifier: Programming Language :: Python :: 3
Requires-Dist: inquirer (>=2.9.2,<3.0.0)
Requires-Dist: result (>=0.7.0,<0.8.0)
Requires-Dist: rich (>=11.0.0,<12.0.0)
Project-URL: Repository, https://github.com/mattcoding4days/vsm
